[
  {
    "url": "https://i.waifu.pics/vw_K35b.gif"
  },
  {
    "url": "https://i.waifu.pics/7lhMNMV.gif"
  },
  {
    "url": "https://i.waifu.pics/YYe0Rml.gif"
  },
  {
    "url": "https://i.waifu.pics/GLm_Nfb.gif"
  },
  {
    "url": "https://i.waifu.pics/nVWsV8D.gif"
  },
  {
    "url": "https://i.waifu.pics/wSJHUmH.gif"
  },
  {
    "url": "https://i.waifu.pics/7cidfnD.gif"
  },
  {
    "url": "https://i.waifu.pics/HxbnbPv.gif"
  },
  {
    "url": "https://i.waifu.pics/Tlsghw~.gif"
  },
  {
    "url": "https://i.waifu.pics/qdzUJAS.gif"
  },
  {
    "url": "https://i.waifu.pics/4RMgMWL.gif"
  },
  {
    "url": "https://i.waifu.pics/Eh5rPXy.gif"
  },
  {
    "url": "https://i.waifu.pics/IwFyG-q.gif"
  },
  {
    "url": "https://i.waifu.pics/SA76sB8.gif"
  },
  {
    "url": "https://i.waifu.pics/Eh5rPXy.gif"
  },
  {
    "url": "https://i.waifu.pics/IwFyG-q.gif"
  },
  {
    "url": "https://i.waifu.pics/4yP6vNQ.gif"
  },
  {
    "url": "https://i.waifu.pics/7lhMNMV.gif"
  },
  {
    "url": "https://i.waifu.pics/KZAo-Va.gif"
  },
  {
    "url": "https://i.waifu.pics/7-IijAs.gif"
  },
  {
    "url": "https://i.waifu.pics/xyuju7Q.gif"
  },
  {
    "url": "https://i.waifu.pics/6ymHeV~.gif"
  },
  {
    "url": "https://i.waifu.pics/Eh5rPXy.gif"
  },
  {
    "url": "https://i.waifu.pics/zSi00LL.gif"
  },
  {
    "url": "https://i.waifu.pics/606vZkF.gif"
  },
  {
    "url": "https://i.waifu.pics/YSXDI2N.gif"
  },
  {
    "url": "https://i.waifu.pics/zSHfe_p.gif"
  },
  {
    "url": "https://i.waifu.pics/pfs3Rr8.gif"
  },
  {
    "url": "https://i.waifu.pics/WMsGAJX.gif"
  },
  {
    "url": "https://i.waifu.pics/606vZkF.gif"
  },
  {
    "url": "https://i.waifu.pics/4yP6vNQ.gif"
  },
  {
    "url": "https://i.waifu.pics/xkSIwtZ.gif"
  },
  {
    "url": "https://i.waifu.pics/Ix3HkVJ.gif"
  },
  {
    "url": "https://i.waifu.pics/Kd0~WdT.gif"
  },
  {
    "url": "https://i.waifu.pics/IwFyG-q.gif"
  },
  {
    "url": "https://i.waifu.pics/ozIc0J9.gif"
  },
  {
    "url": "https://i.waifu.pics/YSXDI2N.gif"
  },
  {
    "url": "https://i.waifu.pics/7g-0qVN.gif"
  },
  {
    "url": "https://i.waifu.pics/Icwz5Uj.gif"
  },
  {
    "url": "https://i.waifu.pics/WlgtakZ.gif"
  },
  {
    "url": "https://i.waifu.pics/WlgtakZ.gif"
  },
  {
    "url": "https://i.waifu.pics/mhLpKn5.gif"
  },
  {
    "url": "https://i.waifu.pics/YYe0Rml.gif"
  },
  {
    "url": "https://i.waifu.pics/b7Udrxl.gif"
  },
  {
    "url": "https://i.waifu.pics/WlgtakZ.gif"
  },
  {
    "url": "https://i.waifu.pics/55G-iDD.gif"
  },
  {
    "url": "https://i.waifu.pics/GLm_Nfb.gif"
  },
  {
    "url": "https://i.waifu.pics/nVWsV8D.gif"
  },
  {
    "url": "https://i.waifu.pics/HxbnbPv.gif"
  }
]
